unifi_tools/__init__.py
unifi_tools/config.py
unifi_tools/features.py
unifi_tools/logging.py
unifi_tools/run.py
unifi_tools/unifi.py
unifi_tools/version.py
unifi_tools/installer/etc/systemd/system/unifi-tools.service
unifi_tools/installer/etc/unifi/settings.yaml
unifi_tools/plugins/__init__.py
unifi_tools/plugins/features.py
unifi_tools/plugins/hass/__init__.py
unifi_tools/plugins/hass/binary_sensors.py
unifi_tools/plugins/hass/discover.py
unifi_tools/plugins/hass/switches.py
unifi_tools-1.1.1.dist-info/LICENSE
unifi_tools-1.1.1.dist-info/METADATA
unifi_tools-1.1.1.dist-info/WHEEL
unifi_tools-1.1.1.dist-info/entry_points.txt
unifi_tools-1.1.1.dist-info/top_level.txt
unifi_tools-1.1.1.dist-info/RECORD
