Metadata-Version: 2.1
Name: unifi-tools
Version: 1.1.1
Summary: Control UniFi devices with MQTT commands.
Home-page: https://github.com/mh-superbox/unifi-tools
Author: Michael Hacker
Author-email: mh@superbox.one
License: MIT
Classifier: License :: OSI Approved :: MIT License
Classifier: Programming Language :: Python :: 3
Classifier: Programming Language :: Python :: 3.8
Classifier: Programming Language :: Python :: 3 :: Only
Classifier: Operating System :: POSIX :: Linux
Requires-Python: >=3.8
License-File: LICENSE
Requires-Dist: requests (~=2.28.1)
Requires-Dist: superbox-utils (~=0.3.0)
